temboardsched
